xlfparser/__init__.py
xlfparser/_xlfparser.cp37-win32.pyd
xlfparser/_xlfparser.cpp
xlfparser/_xlfparser.pxd
xlfparser/_xlfparser.pyx
xlfparser/ast.py
xlfparser/options.py
xlfparser/token.py
xlfparser-0.0.1.dist-info/LICENSE
xlfparser-0.0.1.dist-info/METADATA
xlfparser-0.0.1.dist-info/WHEEL
xlfparser-0.0.1.dist-info/top_level.txt
xlfparser-0.0.1.dist-info/RECORD
