Metadata-Version: 2.1
Name: xlfparser
Version: 0.0.1
Summary: Excel formula parser.
Home-page: https://github.com/pyxll/xlfparser
Author: Tony Roberts
Author-email: tony@pyxll.com
License: MIT License
License-File: LICENSE
Requires-Dist: Cython
